gen_browser_header/__init__.py
gen_browser_header/helper/Helper.py
gen_browser_header/helper/__init__.py
gen_browser_header/main/GenHeader.py
gen_browser_header/main/GenUA.py
gen_browser_header/main/__init__.py
gen_browser_header/self/SelfConstant.py
gen_browser_header/self/SelfEnum.py
gen_browser_header/self/SelfException.py
gen_browser_header/self/__init__.py
gen_browser_header/setting/Setting.py
gen_browser_header/setting/__init__.py
gen_browser_header/tests/__init__.py
gen_browser_header/tests/test_helper/__init__.py
gen_browser_header/tests/test_helper/test_Helper.py
gen_browser_header-0.1.3.dist-info/LICENSE
gen_browser_header-0.1.3.dist-info/METADATA
gen_browser_header-0.1.3.dist-info/WHEEL
gen_browser_header-0.1.3.dist-info/top_level.txt
gen_browser_header-0.1.3.dist-info/RECORD
