Metadata-Version: 2.1
Name: gen-browser-header
Version: 0.1.3
Summary: A package to generate http(s) request header
Home-page: https://github.com/zwzw911/gen-browser-header
Author: zwzw911
Author-email: zwzw911110@163.com
License: UNKNOWN
Platform: UNKNOWN
Classifier: Programming Language :: Python :: 3
Classifier: License :: OSI Approved :: MIT License
Classifier: Operating System :: Microsoft :: Windows
Requires-Python: >=3.6
